vectorose/__init__.py
vectorose/data/__init__.py
vectorose/data/cluster_girdle.npy
vectorose/data/twisted_blocks.npy
vectorose/data/two_clusters.npy
vectorose/io.py
vectorose/mock_data.py
vectorose/plotting.py
vectorose/polar_data.py
vectorose/sphere_base.py
vectorose/stats.py
vectorose/tregenza_sphere.py
vectorose/triangle_sphere.py
vectorose/util.py
vectorose-1.4.2.dist-info/METADATA
vectorose-1.4.2.dist-info/WHEEL
vectorose-1.4.2.dist-info/licenses/LICENSE
vectorose-1.4.2.dist-info/RECORD
