Metadata-Version: 2.4
Name: vectorose
Version: 1.4.2
Summary: Plot polar and spherical histograms from orientation data.
License-Expression: MIT
License-File: LICENSE
Author: Benjamin Z. Rudski
Author-email: benjamin.rudski@mail.mcgill.ca
Requires-Python: >=3.10
Classifier: Programming Language :: Python :: 3
Classifier: Programming Language :: Python :: 3.10
Classifier: Programming Language :: Python :: 3.11
Classifier: Programming Language :: Python :: 3.12
Classifier: Programming Language :: Python :: 3.13
Classifier: Programming Language :: Python :: 3.14
Requires-Dist: imageio-ffmpeg (>=0.5.1,<1)
Requires-Dist: imageio[ffmpeg,pyav] (>=2.27.0)
Requires-Dist: importlib-metadata (>=7.0.1)
Requires-Dist: ipywidgets (>=8.1.5,<9)
Requires-Dist: matplotlib (>=3.3.4)
Requires-Dist: numpy (>=1.19.5)
Requires-Dist: openpyxl (>=3.1.2,<4)
Requires-Dist: pandas (>=1.1.3)
Requires-Dist: pyvista[all,jupyter] (>=0.44.1,<1)
Requires-Dist: scipy (>=1.14,<2)
Requires-Dist: tables (>=3.10.1,<4.0.0)
Requires-Dist: trame (>=3.6.5,<4)
Requires-Dist: trimesh[easy] (>=4.3.0,<5)
Project-URL: Bug Tracker, https://github.com/bzrudski/vectorose/issues
Project-URL: Documentation, https://vectorose.readthedocs.io/en/latest/index.html
Project-URL: Homepage, https://github.com/bzrudski/vectorose
Project-URL: Repository, https://github.com/bzrudski/vectorose
